LICENSE
README.md
setup.py
selenium_po/__init__.py
selenium_po/elementoperator.py
selenium_po.egg-info/PKG-INFO
selenium_po.egg-info/SOURCES.txt
selenium_po.egg-info/dependency_links.txt
selenium_po.egg-info/requires.txt
selenium_po.egg-info/top_level.txt