Metadata-Version: 2.1
Name: selenium-po
Version: 0.0.6
Summary: 使用yaml实现selenium的po
Home-page: https://github.com/zx490336534/selenium-po
Author: zhong xin
Author-email: 490336534@qq.com
License: UNKNOWN
Platform: UNKNOWN
Classifier: Programming Language :: Python :: 3
Classifier: License :: OSI Approved :: MIT License
Classifier: Operating System :: OS Independent
Requires-Python: >=3.6
License-File: LICENSE
